shlink/__init__.py
shlink/request.py
shlink/shlink.py
PyShlink-0.2.1.dist-info/LICENSE
PyShlink-0.2.1.dist-info/METADATA
PyShlink-0.2.1.dist-info/WHEEL
PyShlink-0.2.1.dist-info/top_level.txt
PyShlink-0.2.1.dist-info/RECORD
