Metadata-Version: 2.1
Name: PyShlink
Version: 0.2.1
Summary: Library to extract information from Shlink
Home-page: https://github.com/Andes-hosting/PyShlink
Author: Victor Díaz, Gonzalo Moyano
Author-email: vmdcortes@gmail.com, gonzalomhenriquez13@gmail.com
Keywords: python,shlink,api
Classifier: Programming Language :: Python :: 3
Classifier: License :: OSI Approved :: MIT License
Classifier: Natural Language :: English
Classifier: Operating System :: OS Independent
Requires-Python: >=3.6
License-File: LICENSE
Requires-Dist: requests ==2.31.0
Requires-Dist: typing-extensions ==4.8.0
